infoblox_exporter/__init__.py
infoblox_exporter/__main__.py
infoblox_exporter/api.py
infoblox_exporter/dhcp_utilization.py
infoblox_exporter/exceptions.py
infoblox_exporter/infoblox.py
infoblox_exporter/infoblox_status.py
infoblox_exporter/node_info.py
infoblox_exporter/proxy.py
infoblox_exporter/server_config.py
infoblox_exporter/transform.py
infoblox_exporter-0.1.5.dist-info/LICENSE
infoblox_exporter-0.1.5.dist-info/METADATA
infoblox_exporter-0.1.5.dist-info/WHEEL
infoblox_exporter-0.1.5.dist-info/top_level.txt
infoblox_exporter-0.1.5.dist-info/RECORD
